oscillator_snap/__init__.py
oscillator_snap/oscillator_auxiliaries.py
oscillator_snap/oscillator_gauge.py
oscillator_snap/oscillator_snap.py
oscillator_snap-1.0.dist-info/LICENSE
oscillator_snap-1.0.dist-info/METADATA
oscillator_snap-1.0.dist-info/WHEEL
oscillator_snap-1.0.dist-info/top_level.txt
oscillator_snap-1.0.dist-info/RECORD
