Metadata-Version: 2.1
Name: oscillator-snap
Version: 1.0
Summary: Make a snapshot of an oscillator through its time series
Home-page: UNKNOWN
Author: Rok Cestnik
Author-email: rokcestn@uni-potsdam.de
License: MIT
Platform: UNKNOWN
Requires-Dist: tensorflow
Requires-Dist: keras
Requires-Dist: numpy
Requires-Dist: scipy
Requires-Dist: h5py
Requires-Dist: dill
